slurmq/__init__.py
slurmq/__main__.py
slurmq/cli/__init__.py
slurmq/cli/commands/__init__.py
slurmq/cli/commands/check.py
slurmq/cli/commands/config.py
slurmq/cli/commands/efficiency.py
slurmq/cli/commands/monitor.py
slurmq/cli/commands/report.py
slurmq/cli/commands/stats.py
slurmq/cli/main.py
slurmq/cli/ui/__init__.py
slurmq/core/__init__.py
slurmq/core/config.py
slurmq/core/models.py
slurmq/core/quota.py
slurmq/utils/__init__.py
slurmq-0.0.3.dist-info/WHEEL
slurmq-0.0.3.dist-info/entry_points.txt
slurmq-0.0.3.dist-info/METADATA
slurmq-0.0.3.dist-info/RECORD
