Metadata-Version: 2.4
Name: slurmq
Version: 0.0.3
Summary: Quota monitoring and management for Slurm.
Keywords: slurm,hpc,gpu,quota,monitoring
Author: Dedalus Labs
Author-email: Dedalus Labs <oss@dedaluslabs.ai>
License-Expression: MIT
Classifier: Development Status :: 3 - Alpha
Classifier: Environment :: Console
Classifier: Intended Audience :: System Administrators
Classifier: License :: OSI Approved :: MIT License
Classifier: Operating System :: POSIX :: Linux
Classifier: Programming Language :: Python :: 3.11
Classifier: Programming Language :: Python :: 3.12
Classifier: Programming Language :: Python :: 3.13
Classifier: Programming Language :: Python :: 3.14
Classifier: Topic :: System :: Clustering
Classifier: Topic :: System :: Monitoring
Requires-Dist: typer>=0.12
Requires-Dist: rich>=13.0
Requires-Dist: textual>=0.50
Requires-Dist: pydantic>=2.0
Requires-Dist: pydantic-settings>=2.0
Requires-Dist: tomli-w>=1.0
Requires-Dist: pandas>=2.0
Requires-Dist: tabulate>=0.9
Requires-Dist: platformdirs>=4.0
Requires-Dist: pytest>=8.0 ; extra == 'dev'
Requires-Dist: pytest-cov>=4.0 ; extra == 'dev'
Requires-Dist: ruff>=0.4 ; extra == 'dev'
Requires-Dist: ty>=0.0.6 ; extra == 'dev'
Requires-Dist: pre-commit>=4.0 ; extra == 'dev'
Requires-Dist: mkdocs>=1.6 ; extra == 'docs'
Requires-Dist: mkdocs-material>=9.5 ; extra == 'docs'
Requires-Dist: mkdocstrings[python]>=0.25 ; extra == 'docs'
Requires-Dist: mkdocs-llmstxt>=0.2 ; extra == 'docs'
Requires-Dist: mkdocs-git-revision-date-localized-plugin>=1.2 ; extra == 'docs'
Requires-Dist: pymdown-extensions>=10.0 ; extra == 'docs'
Requires-Python: >=3.11
Project-URL: Documentation, https://dedalus-labs.github.io/slurmq
Project-URL: Homepage, https://github.com/dedalus-labs/slurmq
Project-URL: Issues, https://github.com/dedalus-labs/slurmq/issues
Project-URL: Repository, https://github.com/dedalus-labs/slurmq.git
Provides-Extra: dev
Provides-Extra: docs
